shipyard_mysql/__init__.py
shipyard_mysql/cli/__init__.py
shipyard_mysql/cli/authtest.py
shipyard_mysql/cli/execute_sql.py
shipyard_mysql/cli/store_query_results.py
shipyard_mysql/cli/upload_file.py
shipyard_mysql/mysql.py
shipyard_mysql-0.1.0.dist-info/METADATA
shipyard_mysql-0.1.0.dist-info/WHEEL
shipyard_mysql-0.1.0.dist-info/RECORD
